pep3134-0.1.4.dist-info/top_level.txt
pep3134-0.1.4.dist-info/WHEEL
pep3134-0.1.4.dist-info/metadata.json
pep3134-0.1.4.dist-info/METADATA
pep3134-0.1.4.dist-info/RECORD
pep3134-0.1.4.dist-info/DESCRIPTION.rst
pep3134/utils.py
pep3134/py3.py
pep3134/__init__.py
pep3134/py2.py
